oschecks/neutron.py
oschecks/ceilometer.py
oschecks/keystone.py
oschecks/__init__.py
oschecks/glance.py
oschecks/amqp.py
oschecks/process.py
oschecks/nova.py
oschecks/cinder.py
oschecks/pacemaker_host_check.py
oschecks/ceph.py
oschecks/utils.py
oschecks/tests/__init__.py
oschecks/tests/test_ceph.py
oschecks/tests/test_script.py
monitoring_for_openstack-1.0.0.dist-info/WHEEL
monitoring_for_openstack-1.0.0.dist-info/metadata.json
monitoring_for_openstack-1.0.0.dist-info/entry_points.txt
monitoring_for_openstack-1.0.0.dist-info/METADATA
monitoring_for_openstack-1.0.0.dist-info/RECORD
monitoring_for_openstack-1.0.0.dist-info/DESCRIPTION.rst
monitoring_for_openstack-1.0.0.dist-info/pbr.json
monitoring_for_openstack-1.0.0.dist-info/top_level.txt
monitoring_for_openstack-1.0.0.data/scripts/oschecks-check_swift
monitoring_for_openstack-1.0.0.data/scripts/oschecks-check_horizon_login
monitoring_for_openstack-1.0.0.data/scripts/oschecks-check_swift_recon
monitoring_for_openstack-1.0.0.data/scripts/oschecks-check_swift_dispersion
monitoring_for_openstack-1.0.0.data/scripts/oschecks-check_swift_object_servers
monitoring_for_openstack-1.0.0.data/scripts/oschecks-check_swift_ring_usage
