Metadata-Version: 2.0
Name: monitoring-for-openstack
Version: 1.0.0
Summary: OpenStack monitoring tools
Home-page: UNKNOWN
Author: eNovance
Author-email: techs@enovance.com
License: UNKNOWN
Platform: UNKNOWN
Classifier: Environment :: OpenStack
Classifier: Intended Audience :: Information Technology
Classifier: Intended Audience :: System Administrators
Classifier: License :: OSI Approved :: Apache Software License
Classifier: Operating System :: POSIX :: Linux
Classifier: Programming Language :: Python
Classifier: Programming Language :: Python :: 2
Classifier: Programming Language :: Python :: 2.6
Classifier: Programming Language :: Python :: 2.7
Classifier: Programming Language :: Python :: 3.3
Classifier: Programming Language :: Python :: 3.4
Classifier: Topic :: System :: Monitoring
Requires-Dist: psutil
Requires-Dist: python-ceilometerclient
Requires-Dist: python-cinderclient
Requires-Dist: python-glanceclient
Requires-Dist: python-keystoneclient
Requires-Dist: python-neutronclient
Requires-Dist: python-novaclient
Requires-Dist: six
